conkits/__init__.py
conkits/__main__.py
conkits/ansi.py
conkits/conio.py
conkits/ansi256colors/__init__.py
conkits/ansi256colors/ansi256colors.py
conkits/ansi256colors/ansi256colorscodes.py
conkits/help/__init__.py
conkits/help/anim.py
conkits/help/predefinedcolors.py
conkits/help/usage.py
conkits/printtools/__init__.py
conkits/printtools/ansistring.py
conkits/printtools/basicprinttool.py
conkits/printtools/dynamicprint.py
conkits-0.2.2.dist-info/LICENSE
conkits-0.2.2.dist-info/METADATA
conkits-0.2.2.dist-info/WHEEL
conkits-0.2.2.dist-info/top_level.txt
conkits-0.2.2.dist-info/RECORD
