Metadata-Version: 2.1
Name: conkits
Version: 0.2.2
Summary: 封装了常用的 ANSI 控制码，包括前景色，背景色，光标控制以及一些其他的有趣功能。
Author-email: EKSIlvyAh <1926139610@qq.com>
Project-URL: Homepage, https://github.com/EKSIlvyAh/conkits
Project-URL: Bug Tracker, https://github.com/EKSIlvyAh/conkits/issues
Classifier: Programming Language :: Python :: 3
Classifier: License :: OSI Approved :: MIT License
Classifier: Operating System :: OS Independent
Requires-Python: >=3.6
License-File: LICENSE
